blackamerxs/__init__.py
blackamerxs/amer.py
Blackamerxs-0.1.dist-info/METADATA
Blackamerxs-0.1.dist-info/WHEEL
Blackamerxs-0.1.dist-info/top_level.txt
Blackamerxs-0.1.dist-info/RECORD
